async_handler.py
python_async_handler-0.0.3.dist-info/LICENSE
python_async_handler-0.0.3.dist-info/METADATA
python_async_handler-0.0.3.dist-info/WHEEL
python_async_handler-0.0.3.dist-info/top_level.txt
python_async_handler-0.0.3.dist-info/RECORD
