Metadata-Version: 2.1
Name: python_async_handler
Version: 0.0.3
Summary: A lightweight package allowing developer to easily config their log
Author-email: minhrongcon2000 <minhrongcon2000@gmail.com>
Project-URL: Homepage, https://github.com/minhrongcon2000/python-async-handler
Project-URL: Issues, https://github.com/minhrongcon2000/python-async-handler/issues
Classifier: Programming Language :: Python :: 3
Classifier: License :: OSI Approved :: MIT License
Classifier: Operating System :: OS Independent
Requires-Python: >=3.2
License-File: LICENSE
